setup.cfg
setup.py
src/pymax/__init__.py
src/pymax/__main__.py
src/pymax/cube.py
src/pymax/messages.py
src/pymax/objects.py
src/pymax/response.py
src/pymax/util.py
src/pymax.egg-info/PKG-INFO
src/pymax.egg-info/SOURCES.txt
src/pymax.egg-info/dependency_links.txt
src/pymax.egg-info/not-zip-safe
src/pymax.egg-info/top_level.txt