Metadata-Version: 1.1
Name: pymax
Version: 0.4
Summary: Python implementation of the ELV MAX! Cube API
Home-page: https://ercpe.de/projects/pymax
Author: Johann Schmitz
Author-email: johann@j-schmitz.net
License: GPL-3
Download-URL: https://github.com/ercpe/pymax/tarball/0.4
Platform: UNKNOWN
